with_context/__init__.py
with_context/__main__.py
with_context/__version__.py
with_context-0.dist-info/entry_points.txt
with_context-0.dist-info/LICENSE
with_context-0.dist-info/WHEEL
with_context-0.dist-info/METADATA
with_context-0.dist-info/RECORD
